[
  {
    "code": "002471",
    "name": "中超控股",
    "market_cap": 103.752008,
    "industry": NaN,
    "signal": true,
    "signals": [
      "原始B1"
    ],
    "K": 40.80695496036861,
    "D": 58.65450979743048,
    "J": 5.111845286244858,
    "RSI": 34.53397178531687,
    "near_amplitude": 99.38016528925621,
    "far_amplitude": 138.27160493827162,
    "raw_data": {
      "date": "2026-01-16",
      "open": 7.37,
      "high": 7.85,
      "low": 7.36,
      "close": 7.58,
      "volume": 2821424
    }
  },
  {
    "code": "002965",
    "name": "祥鑫科技",
    "market_cap": 110.50438149,
    "industry": NaN,
    "signal": true,
    "signals": [
      "超卖缩量拐头B"
    ],
    "K": 44.405953742469855,
    "D": 55.72901215727751,
    "J": 21.759836912854553,
    "RSI": 59.69832592597418,
    "near_amplitude": 21.39275766016713,
    "far_amplitude": 23.003104713519612,
    "raw_data": {
      "date": "2026-01-16",
      "open": 40.92,
      "high": 41.9,
      "low": 40.8,
      "close": 41.64,
      "volume": 97628
    }
  },
  {
    "code": "300726",
    "name": "宏达电子",
    "market_cap": 214.44500729,
    "industry": NaN,
    "signal": true,
    "signals": [
      "超卖缩量拐头B"
    ],
    "K": 36.151306660740204,
    "D": 39.962904746822446,
    "J": 28.52811048857572,
    "RSI": 58.22074876900495,
    "near_amplitude": 52.06982543640897,
    "far_amplitude": 60.727464417501324,
    "raw_data": {
      "date": "2026-01-16",
      "open": 50.94,
      "high": 52.5,
      "low": 50.12,
      "close": 52.07,
      "volume": 125271
    }
  },
  {
    "code": "688981",
    "name": "中芯国际",
    "market_cap": 10159.76269015,
    "industry": NaN,
    "signal": true,
    "signals": [
      "超卖缩量拐头B"
    ],
    "K": 31.902253937816045,
    "D": 40.52146487732046,
    "J": 14.663832058807216,
    "RSI": 64.47140746709053,
    "near_amplitude": 19.450110864745017,
    "far_amplitude": 24.496210020336477,
    "raw_data": {
      "date": "2026-01-16",
      "open": 127.5,
      "high": 128.82,
      "low": 124.88,
      "close": 126.99,
      "volume": 756513
    }
  },
  {
    "code": "300024",
    "name": "机器人",
    "market_cap": 289.79625275,
    "industry": NaN,
    "signal": true,
    "signals": [
      "超卖缩量拐头B"
    ],
    "K": 44.98462922007115,
    "D": 57.805646155466235,
    "J": 19.34259534928097,
    "RSI": 51.43357034477284,
    "near_amplitude": 15.178571428571432,
    "far_amplitude": 17.844092570036537,
    "raw_data": {
      "date": "2026-01-16",
      "open": 18.22,
      "high": 18.65,
      "low": 18.06,
      "close": 18.51,
      "volume": 575399
    }
  },
  {
    "code": "000901",
    "name": "航天科技",
    "market_cap": 223.81567424,
    "industry": NaN,
    "signal": true,
    "signals": [
      "原始B1"
    ],
    "K": 38.8990109256936,
    "D": 57.70024092306725,
    "J": 1.2965509309463101,
    "RSI": 34.62998596154182,
    "near_amplitude": 63.133640552995395,
    "far_amplitude": 102.05479452054793,
    "raw_data": {
      "date": "2026-01-16",
      "open": 28.19,
      "high": 28.99,
      "low": 27.38,
      "close": 28.04,
      "volume": 1045721
    }
  },
  {
    "code": "300814",
    "name": "中富电路",
    "market_cap": 145.39118525,
    "industry": NaN,
    "signal": true,
    "signals": [
      "超卖缩量拐头B"
    ],
    "K": 22.63617930838687,
    "D": 24.81762042491788,
    "J": 18.27329707532484,
    "RSI": 57.14786141492948,
    "near_amplitude": 21.610287950796746,
    "far_amplitude": 50.62240663900415,
    "raw_data": {
      "date": "2026-01-16",
      "open": 75.0,
      "high": 76.61,
      "low": 73.5,
      "close": 75.95,
      "volume": 82339
    }
  },
  {
    "code": "688353",
    "name": "华盛锂电",
    "market_cap": 173.39245,
    "industry": NaN,
    "signal": true,
    "signals": [
      "超卖缩量拐头B"
    ],
    "K": 20.702027576586875,
    "D": 24.93205686664268,
    "J": 12.241968996475272,
    "RSI": 53.375801324807014,
    "near_amplitude": 45.489270868441736,
    "far_amplitude": 177.62851513523196,
    "raw_data": {
      "date": "2026-01-16",
      "open": 105.6,
      "high": 113.0,
      "low": 105.58,
      "close": 108.71,
      "volume": 97928
    }
  },
  {
    "code": "003021",
    "name": "兆威机电",
    "market_cap": 302.01657854,
    "industry": NaN,
    "signal": true,
    "signals": [
      "超卖缩量拐头B"
    ],
    "K": 40.789697569295214,
    "D": 49.23385342914438,
    "J": 23.901385849596878,
    "RSI": 62.66565699849569,
    "near_amplitude": 31.39638304180256,
    "far_amplitude": 32.90683726509396,
    "raw_data": {
      "date": "2026-01-16",
      "open": 123.0,
      "high": 127.38,
      "low": 122.5,
      "close": 125.47,
      "volume": 73569
    }
  },
  {
    "code": "000837",
    "name": "秦川机床",
    "market_cap": 136.58996924,
    "industry": NaN,
    "signal": true,
    "signals": [
      "超卖缩量拐头B"
    ],
    "K": 50.44313553255541,
    "D": 62.984086445369336,
    "J": 25.361233706927564,
    "RSI": 65.67162180066668,
    "near_amplitude": 16.695059625212938,
    "far_amplitude": 18.409680207433006,
    "raw_data": {
      "date": "2026-01-16",
      "open": 13.15,
      "high": 13.44,
      "low": 13.02,
      "close": 13.35,
      "volume": 271401
    }
  },
  {
    "code": "300276",
    "name": "三丰智能",
    "market_cap": 136.46158723,
    "industry": NaN,
    "signal": true,
    "signals": [
      "超卖缩量拐头B"
    ],
    "K": 42.07342476882659,
    "D": 50.22777772236305,
    "J": 25.76471886175368,
    "RSI": 56.86697265759296,
    "near_amplitude": 19.92924528301886,
    "far_amplitude": 23.272727272727273,
    "raw_data": {
      "date": "2026-01-16",
      "open": 9.58,
      "high": 9.88,
      "low": 9.44,
      "close": 9.74,
      "volume": 603764
    }
  },
  {
    "code": "688262",
    "name": "国芯科技",
    "market_cap": 108.39357193,
    "industry": NaN,
    "signal": true,
    "signals": [
      "原始B1"
    ],
    "K": 42.6734308997037,
    "D": 58.40558372187831,
    "J": 11.209125255354493,
    "RSI": 51.61048920304114,
    "near_amplitude": 22.621564482029594,
    "far_amplitude": 30.827067669172912,
    "raw_data": {
      "date": "2026-01-16",
      "open": 31.97,
      "high": 32.78,
      "low": 31.51,
      "close": 32.26,
      "volume": 139686
    }
  }
]